{
  "os":  "Linux-6.8.0-90-generic-x86_64-with-glibc2.39",
  "python":  "CPython 3.11.14",
  "startedAt":  "2026-03-20T21:54:05.800923Z",
  "program":  "-m examples.run_cem",
  "git":  {
    "remote":  "https://github.com/alliegriffith/nonAdv.git",
    "commit":  "d8be8b247d20f845939315006b6bc053e0ebe849"
  },
  "email":  "allie11@stanford.edu",
  "root":  "/home/allie11/SimVBG",
  "host":  "longbeach",
  "executable":  "/home/allie11/miniconda3/envs/sim/bin/python",
  "cpu_count":  64,
  "cpu_count_logical":  128,
  "gpu":  "NVIDIA H100 NVL",
  "gpu_count":  2,
  "disk":  {
    "/":  {
      "total":  "940746641408",
      "used":  "812137930752"
    }
  },
  "memory":  {
    "total":  "540510056448"
  },
  "gpu_nvidia":  [
    {
      "name":  "NVIDIA H100 NVL",
      "memoryTotal":  "100485038080",
      "cudaCores":  16896,
      "architecture":  "Hopper",
      "uuid":  "GPU-87eddc1a-2dbe-1bf5-a80b-4b0dbfe60ad0"
    },
    {
      "name":  "NVIDIA H100 NVL",
      "memoryTotal":  "100485038080",
      "cudaCores":  16896,
      "architecture":  "Hopper",
      "uuid":  "GPU-6a8f7138-4010-077f-7054-017d9e659ef8"
    }
  ],
  "cudaVersion":  "13.0",
  "writerId":  "idjdaoq0epvh92corrgquvg6yta1g88c"
}